easycharts/__init__.py
easycharts/charts.py
easycharts/exceptions.py
easycharts/frontend.py
easycharts-0.106.dist-info/LICENSE
easycharts-0.106.dist-info/METADATA
easycharts-0.106.dist-info/WHEEL
easycharts-0.106.dist-info/top_level.txt
easycharts-0.106.dist-info/RECORD
