Metadata-Version: 2.1
Name: easycharts
Version: 0.106
Summary: Easily create data visualization of static or streaming data
Home-page: https://github.com/codemation/easycharts
Author: Joshua Jamison
Author-email: joshjamison1@gmail.com
License: UNKNOWN
Platform: UNKNOWN
Classifier: Programming Language :: Python :: 3
Classifier: License :: OSI Approved :: MIT License
Classifier: Operating System :: OS Independent
Requires-Python: >=3.7, <4
Requires-Dist: easyrpc (>=0.241)
Requires-Dist: aiopyql (>=0.359)
